CHANGES.rst
MANIFEST.in
README.rst
setup.py
django_model_history.egg-info/PKG-INFO
django_model_history.egg-info/SOURCES.txt
django_model_history.egg-info/dependency_links.txt
django_model_history.egg-info/not-zip-safe
django_model_history.egg-info/top_level.txt
model_history/__init__.py
model_history/admin.py
model_history/models.py
model_history/utils.py