Metadata-Version: 1.1
Name: django-model-history
Version: 0.1.1
Summary: Enable in any Model class an change history of all inserts, updates and deletes
Home-page: https://github.com/goinnn/django-model-history
Author: Pablo Martin
Author-email: goinnn@gmail.com
License: LGPL 3
Keywords: django,model,changes history
Platform: UNKNOWN
Classifier: Development Status :: 4 - Beta
Classifier: Framework :: Django
Classifier: License :: OSI Approved :: GNU Library or Lesser General Public License (LGPL)
Classifier: Programming Language :: Python :: 2
